yolk/__init__.py
yolk/__main__.py
yolk/cli.py
yolk/metadata.py
yolk/pypi.py
yolk/retrying.py
yolk/setuptools_support.py
yolk/six.py
yolk/utils.py
yolk/yolklib.py
yolk1977-0.9.5.dist-info/COPYING
yolk1977-0.9.5.dist-info/METADATA
yolk1977-0.9.5.dist-info/WHEEL
yolk1977-0.9.5.dist-info/entry_points.txt
yolk1977-0.9.5.dist-info/top_level.txt
yolk1977-0.9.5.dist-info/RECORD
