Metadata-Version: 2.1
Name: yolk1977
Version: 0.9.5
Summary: Command-line tool for querying PyPI and Python packages installed on your system.
Home-page: https://github.com/fish2000/yolk
Author: Rob Cakebread
Maintainer: Alexander Bohn
License: BSD License
Keywords: PyPI,setuptools,cheeseshop,distutils,eggs,package,management
Platform: UNKNOWN
Classifier: Development Status :: 5 - Production/Stable
Classifier: Intended Audience :: Developers
Classifier: License :: OSI Approved :: BSD License
Classifier: Programming Language :: Python
Classifier: Programming Language :: Python :: 2
Classifier: Programming Language :: Python :: 2.7
Classifier: Programming Language :: Python :: 3
Classifier: Programming Language :: Python :: 3.4
Classifier: Programming Language :: Python :: 3.5
Classifier: Programming Language :: Python :: 3.6
Classifier: Programming Language :: Python :: 3.7
Classifier: Programming Language :: Python :: 3.8
Classifier: Topic :: Software Development :: Libraries :: Python Modules
